{
 "Expression": {
 "toolType": "Expression",
 "controls": [
 { "id": "1", "name": "Point In 1", "kind": "Point" },
 { "id": "2", "name": "Point In 2", "kind": "Point" },
 { "id": "3", "name": "Point In 3", "kind": "Point" },
 { "id": "4", "name": "Point In 4", "kind": "Point" },
 { "id": "5", "name": "Point In 5", "kind": "Point" },
 { "id": "6", "name": "Point In 6", "kind": "Point" },
 { "id": "7", "name": "Point In 7", "kind": "Point" },
 { "id": "8", "name": "Point In 8", "kind": "Point" },
 { "id": "9", "name": "Point In 9", "kind": "Point" },
 { "id": "10", "name": "Number In 1", "kind": "Number" },
 { "id": "11", "name": "Number In 2", "kind": "Number" },
 { "id": "12", "name": "Number In 3", "kind": "Number" },
 { "id": "13", "name": "Number In 4", "kind": "Number" },
 { "id": "14", "name": "Number In 5", "kind": "Number" },
 { "id": "15", "name": "Number In 6", "kind": "Number" },
 { "id": "16", "name": "Number In 7", "kind": "Number" },
 { "id": "17", "name": "Number In 8", "kind": "Number" },
 { "id": "18", "name": "Number In 9", "kind": "Number" },
 { "id": "19", "name": "Number Expression", "kind": "Text" },
 { "id": "20", "name": "Point Expression X", "kind": "Text" },
 { "id": "21", "name": "Point Expression Y", "kind": "Text" },
 { "id": "22", "name": "Random Seed", "kind": "Number" },
 { "id": "23", "name": "Reseed", "kind": "Number" },
 { "id": "24", "name": "Number Controls", "kind": "Number" },
 { "id": "25", "name": "Show Number 1", "kind": "Number" },
 { "id": "26", "name": "Name for Number 1", "kind": "Text" },
 { "id": "27", "name": "Show Number 2", "kind": "Number" },
 { "id": "28", "name": "Name for Number 2", "kind": "Text" },
 { "id": "29", "name": "Show Number 3", "kind": "Number" },
 { "id": "30", "name": "Name for Number 3", "kind": "Text" },
 { "id": "31", "name": "Show Number 4", "kind": "Number" },
 { "id": "32", "name": "Name for Number 4", "kind": "Text" },
 { "id": "33", "name": "Show Number 5", "kind": "Number" },
 { "id": "34", "name": "Name for Number 5", "kind": "Text" },
 { "id": "35", "name": "Show Number 6", "kind": "Number" },
 { "id": "36", "name": "Name for Number 6", "kind": "Text" },
 { "id": "37", "name": "Show Number 7", "kind": "Number" },
 { "id": "38", "name": "Name for Number 7", "kind": "Text" },
 { "id": "39", "name": "Show Number 8", "kind": "Number" },
 { "id": "40", "name": "Name for Number 8", "kind": "Text" },
 { "id": "41", "name": "Show Number 9", "kind": "Number" },
 { "id": "42", "name": "Name for Number 9", "kind": "Text" },
 { "id": "43", "name": "Point Controls", "kind": "Number" },
 { "id": "44", "name": "Show Point 1", "kind": "Number" },
 { "id": "45", "name": "Name for Point 1", "kind": "Text" },
 { "id": "46", "name": "Show Point 2", "kind": "Number" },
 { "id": "47", "name": "Name for Point 2", "kind": "Text" },
 { "id": "48", "name": "Show Point 3", "kind": "Number" },
 { "id": "49", "name": "Name for Point 3", "kind": "Text" },
 { "id": "50", "name": "Show Point 4", "kind": "Number" },
 { "id": "51", "name": "Name for Point 4", "kind": "Text" },
 { "id": "52", "name": "Show Point 5", "kind": "Number" },
 { "id": "53", "name": "Name for Point 5", "kind": "Text" },
 { "id": "54", "name": "Show Point 6", "kind": "Number" },
 { "id": "55", "name": "Name for Point 6", "kind": "Text" },
 { "id": "56", "name": "Show Point 7", "kind": "Number" },
 { "id": "57", "name": "Name for Point 7", "kind": "Text" },
 { "id": "58", "name": "Show Point 8", "kind": "Number" },
 { "id": "59", "name": "Name for Point 8", "kind": "Text" },
 { "id": "60", "name": "Show Point 9", "kind": "Number" },
 { "id": "61", "name": "Name for Point 9", "kind": "Text" },
 { "id": "62", "name": "Comments", "kind": "Number" },
 { "id": "63", "name": "Comments", "kind": "Text" },
 { "id": "64", "name": "Frame Render Script", "kind": "Number" },
 { "id": "65", "name": "Frame Render Script", "kind": "Text" },
 { "id": "66", "name": "Start Render Scripts", "kind": "Number" },
 { "id": "67", "name": "Start Render Script", "kind": "Text" },
 { "id": "68", "name": "End Render Scripts", "kind": "Number" },
 { "id": "69", "name": "End Render Script", "kind": "Text" }
 ]
 },
 "LUTBezier": {
 "toolType": "LUTBezier",
 "controls": [
 { "id": "1", "name": "Color Change", "kind": "Number" }
 ]
 },
 "LUTLookup": {
 "toolType": "LUTLookup",
 "controls": [
 { "id": "1", "name": "Curve Shape", "kind": "Number" },
 { "id": "2", "name": "Source", "kind": "FuID" },
 { "id": "3", "name": "Input", "kind": "Number" },
 { "id": "4", "name": "Curve", "kind": "FuID" },
 { "id": "5", "name": "In / Out", "kind": "FuID" },
 { "id": "6", "name": "Out", "kind": "FuID" },
 { "id": "7", "name": "Lookup", "kind": "LookUpTable" },
 { "id": "8", "name": "Mirror", "kind": "Number" },
 { "id": "9", "name": "Invert", "kind": "Number" },
 { "id": "10", "name": "Scaling", "kind": "Number" },
 { "id": "11", "name": "Scale", "kind": "Number" },
 { "id": "12", "name": "Offset", "kind": "Number" },
 { "id": "13", "name": "Clip Low", "kind": "Number" },
 { "id": "14", "name": "Clip High", "kind": "Number" },
 { "id": "15", "name": "Timing", "kind": "Number" },
 { "id": "16", "name": "Time Scale", "kind": "Number" },
 { "id": "17", "name": "Time Offset", "kind": "Number" },
 { "id": "18", "name": "Comments", "kind": "Number" },
 { "id": "19", "name": "Comments", "kind": "Text" },
 { "id": "20", "name": "Frame Render Script", "kind": "Number" },
 { "id": "21", "name": "Frame Render Script", "kind": "Text" },
 { "id": "22", "name": "Start Render Scripts", "kind": "Number" },
 { "id": "23", "name": "Start Render Script", "kind": "Text" },
 { "id": "24", "name": "End Render Scripts", "kind": "Number" },
 { "id": "25", "name": "End Render Script", "kind": "Text" }
 ]
 },
 "Offset": {
 "toolType": "Offset",
 "controls": [
 { "id": "1", "name": "Position", "kind": "Point" },
 { "id": "2", "name": "Offset", "kind": "Point" },
 { "id": "3", "name": "Flip Pos Horiz", "kind": "Number" },
 { "id": "4", "name": "Flip Pos Vert", "kind": "Number" },
 { "id": "5", "name": "Flip Offset Horiz", "kind": "Number" },
 { "id": "6", "name": "Flip Offset Vert", "kind": "Number" },
 { "id": "7", "name": "Mode", "kind": "Number" },
 { "id": "8", "name": "Angle and Distance", "kind": "Number" },
 { "id": "9", "name": "Image Aspect", "kind": "Number" },
 { "id": "10", "name": "Angle Scale", "kind": "Number" },
 { "id": "11", "name": "Angle Offset", "kind": "Number" },
 { "id": "12", "name": "Distance Scale", "kind": "Number" },
 { "id": "13", "name": "Distance Offset", "kind": "Number" },
 { "id": "14", "name": "Angle/Distance Mode", "kind": "FuID" },
 { "id": "15", "name": "Position Time Scale", "kind": "Number" },
 { "id": "16", "name": "Position Time Offset", "kind": "Number" },
 { "id": "17", "name": "Offset Time Scale", "kind": "Number" },
 { "id": "18", "name": "Offset Time Offset", "kind": "Number" },
 { "id": "19", "name": "Comments", "kind": "Number" },
 { "id": "20", "name": "Comments", "kind": "Text" },
 { "id": "21", "name": "Frame Render Script", "kind": "Number" },
 { "id": "22", "name": "Frame Render Script", "kind": "Text" },
 { "id": "23", "name": "Start Render Scripts", "kind": "Number" },
 { "id": "24", "name": "Start Render Script", "kind": "Text" },
 { "id": "25", "name": "End Render Scripts", "kind": "Number" },
 { "id": "26", "name": "End Render Script", "kind": "Text" }
 ]
 },
 "PerturbPoint": {
 "toolType": "PerturbPoint",
 "controls": [
 { "id": "1", "name": "Value", "kind": "Point" },
 { "id": "2", "name": "X Scale", "kind": "Number" },
 { "id": "3", "name": "Y Scale", "kind": "Number" },
 { "id": "4", "name": "Random Seed", "kind": "Number" },
 { "id": "5", "name": "Reseed", "kind": "Number" },
 { "id": "6", "name": "Strength", "kind": "Number" },
 { "id": "7", "name": "Wobble", "kind": "Number" },
 { "id": "8", "name": "Speed", "kind": "Number" },
 { "id": "9", "name": "Comments", "kind": "Number" },
 { "id": "10", "name": "Comments", "kind": "Text" },
 { "id": "11", "name": "Frame Render Script", "kind": "Number" },
 { "id": "12", "name": "Frame Render Script", "kind": "Text" },
 { "id": "13", "name": "Start Render Scripts", "kind": "Number" },
 { "id": "14", "name": "Start Render Script", "kind": "Text" },
 { "id": "15", "name": "End Render Scripts", "kind": "Number" },
 { "id": "16", "name": "End Render Script", "kind": "Text" }
 ]
 },
 "PublishNumber": {
 "toolType": "PublishNumber",
 "controls": [
 { "id": "1", "name": "Value", "kind": "Number" },
 { "id": "2", "name": "Comments", "kind": "Number" },
 { "id": "3", "name": "Comments", "kind": "Text" },
 { "id": "4", "name": "Frame Render Script", "kind": "Number" },
 { "id": "5", "name": "Frame Render Script", "kind": "Text" },
 { "id": "6", "name": "Start Render Scripts", "kind": "Number" },
 { "id": "7", "name": "Start Render Script", "kind": "Text" },
 { "id": "8", "name": "End Render Scripts", "kind": "Number" },
 { "id": "9", "name": "End Render Script", "kind": "Text" }
 ]
 },
 "PublishPoint": {
 "toolType": "PublishPoint",
 "controls": [
 { "id": "1", "name": "Value", "kind": "Point" },
 { "id": "2", "name": "Comments", "kind": "Number" },
 { "id": "3", "name": "Comments", "kind": "Text" },
 { "id": "4", "name": "Frame Render Script", "kind": "Number" },
 { "id": "5", "name": "Frame Render Script", "kind": "Text" },
 { "id": "6", "name": "Start Render Scripts", "kind": "Number" },
 { "id": "7", "name": "Start Render Script", "kind": "Text" },
 { "id": "8", "name": "End Render Scripts", "kind": "Number" },
 { "id": "9", "name": "End Render Script", "kind": "Text" }
 ]
 },
 "PublishText": {
 "toolType": "PublishText",
 "controls": [
 { "id": "1", "name": "Value", "kind": "Number" },
 { "id": "2", "name": "Value", "kind": "Text" },
 { "id": "3", "name": "Comments", "kind": "Number" },
 { "id": "4", "name": "Comments", "kind": "Text" },
 { "id": "5", "name": "Frame Render Script", "kind": "Number" },
 { "id": "6", "name": "Frame Render Script", "kind": "Text" },
 { "id": "7", "name": "Start Render Scripts", "kind": "Number" },
 { "id": "8", "name": "Start Render Script", "kind": "Text" },
 { "id": "9", "name": "End Render Scripts", "kind": "Number" },
 { "id": "10", "name": "End Render Script", "kind": "Text" }
 ]
 },
 "Shake": {
 "toolType": "Shake",
 "controls": [
 { "id": "1", "name": "Random Seed", "kind": "Number" },
 { "id": "2", "name": "Reseed", "kind": "Number" },
 { "id": "3", "name": "Smoothness", "kind": "Number" },
 { "id": "4", "name": "Lock X/Y", "kind": "Number" },
 { "id": "5", "name": "Minimum", "kind": "Number" },
 { "id": "6", "name": "Maximum", "kind": "Number" },
 { "id": "7", "name": "Y Minimum", "kind": "Number" },
 { "id": "8", "name": "Y Maximum", "kind": "Number" },
 { "id": "9", "name": "Comments", "kind": "Number" },
 { "id": "10", "name": "Comments", "kind": "Text" },
 { "id": "11", "name": "Frame Render Script", "kind": "Number" },
 { "id": "12", "name": "Frame Render Script", "kind": "Text" },
 { "id": "13", "name": "Start Render Scripts", "kind": "Number" },
 { "id": "14", "name": "Start Render Script", "kind": "Text" },
 { "id": "15", "name": "End Render Scripts", "kind": "Number" },
 { "id": "16", "name": "End Render Script", "kind": "Text" }
 ]
 }
}
